sokudoku.py
sokudoku-0.0.4.dist-info/LICENSE.txt
sokudoku-0.0.4.dist-info/METADATA
sokudoku-0.0.4.dist-info/WHEEL
sokudoku-0.0.4.dist-info/entry_points.txt
sokudoku-0.0.4.dist-info/top_level.txt
sokudoku-0.0.4.dist-info/RECORD
