Metadata-Version: 2.1
Name: sokudoku
Version: 0.0.4
Summary: PyPI test 
Home-page: https://github.com/Hikaru163/cs_ai
Author: tomihara hikaru
Author-email: s2122041@stu.musashino-u.ac.jp
License: UNKNOWN
Project-URL: Bug Tracker, https://github.com/Hikaru163/cs_ai
Platform: UNKNOWN
Classifier: Programming Language :: Python :: 3
Classifier: License :: OSI Approved :: MIT License
Classifier: Operating System :: OS Independent
Requires-Python: >=3.7
